dask_memusage.py
dask_memusage-1.1.dist-info/LICENSE
dask_memusage-1.1.dist-info/WHEEL
dask_memusage-1.1.dist-info/METADATA
dask_memusage-1.1.dist-info/RECORD
