Metadata-Version: 2.1
Name: dask_memusage
Version: 1.1
Summary: Low-impact, task-level memory profiling for Dask.
Home-page: https://github.com/itamarst/dask-memusage
License: UNKNOWN
Author: Itamar Turner-Trauring
Author-email: itamar@itamarst.org
Requires-Python: >=3.6
Classifier: Programming Language :: Python :: 3
Classifier: License :: OSI Approved :: MIT License
Requires-Dist: distributed
Requires-Dist: click
Requires-Dist: pytest ; extra == "test"
Requires-Dist: flake8 ; extra == "test"
Requires-Dist: numpy ; extra == "test"
Requires-Dist: dask[bag] ; extra == "test"
Provides-Extra: test
